fair_llm-0.1.0.dist-info/licenses/LICENSE.md
fairlib/__init__.py
fairlib/config/settings.yml
fairlib/core/base_agent.py
fairlib/core/config.py
fairlib/core/config_schemas.py
fairlib/core/message.py
fairlib/core/prompts.py
fairlib/core/types.py
fairlib/core/interfaces/communicator.py
fairlib/core/interfaces/embedder.py
fairlib/core/interfaces/executor.py
fairlib/core/interfaces/llm.py
fairlib/core/interfaces/memory.py
fairlib/core/interfaces/model_manager.py
fairlib/core/interfaces/perception.py
fairlib/core/interfaces/planner.py
fairlib/core/interfaces/security.py
fairlib/core/interfaces/tools.py
fairlib/modules/action/executor.py
fairlib/modules/action/tools/advanced_calculus_tool.py
fairlib/modules/action/tools/code_execution_tool.py
fairlib/modules/action/tools/grading_tool.py
fairlib/modules/action/tools/graphing_tool.py
fairlib/modules/action/tools/knowledge_tool.py
fairlib/modules/action/tools/registry.py
fairlib/modules/action/tools/builtin_tools/data_extractor.py
fairlib/modules/action/tools/builtin_tools/final_answer.py
fairlib/modules/action/tools/builtin_tools/safe_calculator.py
fairlib/modules/action/tools/builtin_tools/weather.py
fairlib/modules/action/tools/builtin_tools/web_searcher.py
fairlib/modules/agent/multi_agent_runner.py
fairlib/modules/agent/simple_agent.py
fairlib/modules/communication/in_memory_communicator.py
fairlib/modules/learning/base.py
fairlib/modules/learning/model_selector.py
fairlib/modules/mal/anthropic_adapter.py
fairlib/modules/mal/huggingface_adapter.py
fairlib/modules/mal/local_llama_adapter.py
fairlib/modules/mal/openai_adapter.py
fairlib/modules/memory/base.py
fairlib/modules/memory/embedder.py
fairlib/modules/memory/retriever.py
fairlib/modules/memory/retriever_rerank.py
fairlib/modules/memory/summarization.py
fairlib/modules/memory/vector_faiss.py
fairlib/modules/memory/vector_store.py
fairlib/modules/perception/echo_preprocessor.py
fairlib/modules/perception/text_parser.py
fairlib/modules/planning/react_planner.py
fairlib/modules/security/basic_security_manager.py
fair_llm-0.1.0.dist-info/METADATA
fair_llm-0.1.0.dist-info/WHEEL
fair_llm-0.1.0.dist-info/top_level.txt
fair_llm-0.1.0.dist-info/RECORD
