Metadata-Version: 2.4
Name: fair-llm
Version: 0.1.0
Author-email: Ryan R <rrabinow@uccs.edu>, Austin W <austin.w@ardentinc.com>, Eli G <elijah.g@ardentinc.com>,  Chad M <Chad.Mello@afacademy.af.edu>
License-Expression: MIT
Project-URL: Homepage, https://github.com/USAFA-AI-Center
Requires-Python: >=3.11
License-File: LICENSE.md
Requires-Dist: accelerate==1.8.1
Requires-Dist: aiohappyeyeballs==2.6.1
Requires-Dist: aiohttp==3.12.13
Requires-Dist: aiosignal==1.3.2
Requires-Dist: annotated-types==0.7.0
Requires-Dist: anyio==4.9.0
Requires-Dist: attrs==25.3.0
Requires-Dist: backoff==2.2.1
Requires-Dist: bcrypt==4.3.0
Requires-Dist: bs4>=0.0.2
Requires-Dist: build==1.2.2.post1
Requires-Dist: cachetools==5.5.2
Requires-Dist: certifi==2025.6.15
Requires-Dist: charset-normalizer==3.4.2
Requires-Dist: chromadb==1.0.13
Requires-Dist: click==8.2.1
Requires-Dist: coloredlogs==15.0.1
Requires-Dist: datasets==3.6.0
Requires-Dist: dill==0.3.8
Requires-Dist: distro==1.9.0
Requires-Dist: durationpy==0.10
Requires-Dist: filelock==3.18.0
Requires-Dist: flatbuffers==25.2.10
Requires-Dist: frozenlist==1.7.0
Requires-Dist: fsspec==2025.3.0
Requires-Dist: google-auth==2.40.3
Requires-Dist: googleapis-common-protos==1.70.0
Requires-Dist: grpcio==1.73.0
Requires-Dist: h11==0.16.0
Requires-Dist: hf-xet==1.1.4
Requires-Dist: httpcore==1.0.9
Requires-Dist: httptools==0.6.4
Requires-Dist: httpx==0.28.1
Requires-Dist: huggingface-hub==0.33.0
Requires-Dist: humanfriendly==10.0
Requires-Dist: idna==3.10
Requires-Dist: importlib-metadata==8.7.0
Requires-Dist: importlib-resources==6.5.2
Requires-Dist: jinja2==3.1.6
Requires-Dist: jiter==0.10.0
Requires-Dist: joblib==1.5.1
Requires-Dist: jsonschema==4.24.0
Requires-Dist: jsonschema-specifications==2025.4.1
Requires-Dist: kubernetes==33.1.0
Requires-Dist: lxml==5.4.0
Requires-Dist: markdown-it-py==3.0.0
Requires-Dist: markupsafe==3.0.2
Requires-Dist: matplotlib>=3.10.3
Requires-Dist: mdurl==0.1.2
Requires-Dist: mmh3==5.1.0
Requires-Dist: mpmath==1.3.0
Requires-Dist: multidict==6.5.0
Requires-Dist: multiprocess==0.70.16
Requires-Dist: networkx==3.5
Requires-Dist: numpy==2.3.0
Requires-Dist: oauthlib==3.3.1
Requires-Dist: onnxruntime==1.22.0
Requires-Dist: openai==1.89.0
Requires-Dist: opentelemetry-api==1.34.1
Requires-Dist: opentelemetry-exporter-otlp-proto-common==1.34.1
Requires-Dist: opentelemetry-exporter-otlp-proto-grpc==1.34.1
Requires-Dist: opentelemetry-proto==1.34.1
Requires-Dist: opentelemetry-sdk==1.34.1
Requires-Dist: opentelemetry-semantic-conventions==0.55b1
Requires-Dist: openpyxl>=3.1.0
Requires-Dist: orjson==3.10.18
Requires-Dist: overrides==7.7.0
Requires-Dist: packaging==25.0
Requires-Dist: pandas==2.3.0
Requires-Dist: pillow==11.2.1
Requires-Dist: posthog==5.4.0
Requires-Dist: propcache==0.3.2
Requires-Dist: protobuf==5.29.5
Requires-Dist: psutil==7.0.0
Requires-Dist: pyarrow==20.0.0
Requires-Dist: pyasn1==0.6.1
Requires-Dist: pyasn1-modules==0.4.2
Requires-Dist: pybase64==1.4.1
Requires-Dist: pydantic==2.11.7
Requires-Dist: pydantic-core==2.33.2
Requires-Dist: pygments==2.19.1
Requires-Dist: pypdf==5.6.0
Requires-Dist: pypdf2>=3.0.1
Requires-Dist: pypika==0.48.9
Requires-Dist: pyproject-hooks==1.2.0
Requires-Dist: python-dateutil==2.9.0.post0
Requires-Dist: python-docx==1.2.0
Requires-Dist: python-dotenv==1.1.0
Requires-Dist: python-pptx==1.0.0
Requires-Dist: pytz==2025.2
Requires-Dist: pyyaml==6.0.2
Requires-Dist: referencing==0.36.2
Requires-Dist: regex==2024.11.6
Requires-Dist: requests==2.32.4
Requires-Dist: requests-oauthlib==2.0.0
Requires-Dist: rich==14.0.0
Requires-Dist: rpds-py==0.25.1
Requires-Dist: rsa==4.9.1
Requires-Dist: safetensors==0.5.3
Requires-Dist: scikit-learn==1.7.0
Requires-Dist: scipy==1.15.3
Requires-Dist: sentence-transformers==4.1.0
Requires-Dist: setuptools==80.9.0
Requires-Dist: shellingham==1.5.4
Requires-Dist: six==1.17.0
Requires-Dist: sniffio==1.3.1
Requires-Dist: sympy==1.14.0
Requires-Dist: tenacity==9.1.2
Requires-Dist: threadpoolctl==3.6.0
Requires-Dist: tiktoken==0.9.0
Requires-Dist: tokenizers==0.21.1
Requires-Dist: torch==2.7.1
Requires-Dist: torchaudio==2.7.1
Requires-Dist: torchvision==0.22.1
Requires-Dist: tqdm==4.67.1
Requires-Dist: transformers==4.52.4
Requires-Dist: typer==0.16.0
Requires-Dist: typing-extensions==4.14.0
Requires-Dist: typing-inspection==0.4.1
Requires-Dist: tzdata==2025.2
Requires-Dist: urllib3==2.5.0
Requires-Dist: uvicorn==0.34.3
Requires-Dist: watchfiles==1.1.0
Requires-Dist: websocket-client==1.8.0
Requires-Dist: websockets==15.0.1
Requires-Dist: xxhash==3.5.0
Requires-Dist: yarl==1.20.1
Requires-Dist: zipp==3.23.0
Dynamic: license-file
